qer/__init__.py
qer/__main__.py
qer/blacklist.py
qer/candidates.py
qer/cmdline.py
qer/compile.py
qer/config.py
qer/dists.py
qer/hash.py
qer/localimport.py
qer/metadata.py
qer/utils.py
qer/versions.py
qer/repos/__init__.py
qer/repos/findlinks.py
qer/repos/multi.py
qer/repos/pypi.py
qer/repos/repository.py
qer/repos/solution.py
qer/repos/source.py
qer-0.8.0.dist-info/LICENSE.txt
qer-0.8.0.dist-info/METADATA
qer-0.8.0.dist-info/WHEEL
qer-0.8.0.dist-info/entry_points.txt
qer-0.8.0.dist-info/top_level.txt
qer-0.8.0.dist-info/RECORD
