Metadata-Version: 2.1
Name: qer
Version: 0.8.0
Summary: Python requirements compiler
Home-page: https://github.com/sputt/qer
Author: Spencer Putt
Author-email: sputt@alumni.iu.edu
License: MIT License
Platform: UNKNOWN
Classifier: Programming Language :: Python
Classifier: Programming Language :: Python :: 2.7
Classifier: Programming Language :: Python :: 3.5
Classifier: Programming Language :: Python :: 3.6
Classifier: Operating System :: OS Independent
Classifier: Environment :: Console
Classifier: Topic :: Software Development
Classifier: Intended Audience :: Developers
Classifier: License :: OSI Approved :: MIT License
Requires-Python: >=2.7, !=3.0.*, !=3.1.*, !=3.2.*, !=3.3.*, !=3.4.*
Requires-Dist: requests
Requires-Dist: six
Requires-Dist: functools32 ; python_version < "3.0"
Requires-Dist: enum34 ; python_version < "3.0"
